coagent/__init__.py
coagent/base_configs/__init__.py
coagent/base_configs/env_config.py
coagent/chat/__init__.py
coagent/chat/agent_chat.py
coagent/chat/base_chat.py
coagent/chat/code_chat.py
coagent/chat/knowledge_chat.py
coagent/chat/llm_chat.py
coagent/chat/search_chat.py
coagent/chat/utils.py
coagent/codechat/__init__.py
coagent/codechat/code_analyzer/__init__.py
coagent/codechat/code_analyzer/code_analyzer.py
coagent/codechat/code_analyzer/code_dedup.py
coagent/codechat/code_analyzer/code_intepreter.py
coagent/codechat/code_analyzer/code_preprocess.py
coagent/codechat/code_analyzer/code_static_analysis.py
coagent/codechat/code_analyzer/language_static_analysis/__init__.py
coagent/codechat/code_analyzer/language_static_analysis/java_static_analysis.py
coagent/codechat/code_crawler/__init__.py
coagent/codechat/code_crawler/dir_crawler.py
coagent/codechat/code_crawler/zip_crawler.py
coagent/codechat/code_search/__init__.py
coagent/codechat/code_search/code_search.py
coagent/codechat/code_search/cypher_generator.py
coagent/codechat/code_search/tagger.py
coagent/codechat/codebase_handler/__init__.py
coagent/codechat/codebase_handler/code_importer.py
coagent/codechat/codebase_handler/codebase_handler.py
coagent/connector/__init__.py
coagent/connector/memory_manager.py
coagent/connector/message_process.py
coagent/connector/utils.py
coagent/connector/actions/__init__.py
coagent/connector/actions/base_action.py
coagent/connector/agents/__init__.py
coagent/connector/agents/base_agent.py
coagent/connector/agents/executor_agent.py
coagent/connector/agents/react_agent.py
coagent/connector/agents/selector_agent.py
coagent/connector/antflow/__init__.py
coagent/connector/antflow/flow.py
coagent/connector/chains/__init__.py
coagent/connector/chains/base_chain.py
coagent/connector/chains/chains.py
coagent/connector/configs/__init__.py
coagent/connector/configs/agent_config.py
coagent/connector/configs/chain_config.py
coagent/connector/configs/phase_config.py
coagent-0.0.4.dist-info/LICENSE.md
coagent-0.0.4.dist-info/METADATA
coagent-0.0.4.dist-info/WHEEL
coagent-0.0.4.dist-info/top_level.txt
coagent-0.0.4.dist-info/RECORD
